wagtail_demo_site/__init__.py
wagtail_demo_site/manage.py
wagtail_demo_site/home/__init__.py
wagtail_demo_site/home/models.py
wagtail_demo_site/home/migrations/0001_initial.py
wagtail_demo_site/home/migrations/0002_create_homepage.py
wagtail_demo_site/home/migrations/__init__.py
wagtail_demo_site/search/__init__.py
wagtail_demo_site/search/views.py
wagtail_demo_site/wagtail_demo_site/__init__.py
wagtail_demo_site/wagtail_demo_site/urls.py
wagtail_demo_site/wagtail_demo_site/wsgi.py
wagtail_demo_site/wagtail_demo_site/settings/__init__.py
wagtail_demo_site/wagtail_demo_site/settings/base.py
wagtail_demo_site/wagtail_demo_site/settings/dev.py
wagtail_demo_site/wagtail_demo_site/settings/production.py
wagtail_demo_site-0.7.dist-info/METADATA
wagtail_demo_site-0.7.dist-info/WHEEL
wagtail_demo_site-0.7.dist-info/top_level.txt
wagtail_demo_site-0.7.dist-info/RECORD
