Metadata-Version: 2.1
Name: wagtail-demo-site
Version: 0.7
Summary: web wagtail site
Home-page: UNKNOWN
Author: Alexandro.by
Author-email: alexander.ermak@celadon.ae
License: MIT
Platform: UNKNOWN
Requires-Dist: psycopg2-binary (==2.8.2)
Requires-Dist: uWSGI (==2.0.18)
Requires-Dist: wagtail (==2.6.1)
Requires-Dist: django-cors-headers (==3.0.2)
Requires-Dist: Django (<2.3,>=2.2)
Requires-Dist: wagtail (<2.7,>=2.6)
